findjobana/SXSperprocesing.py
findjobana/__init__.py
findjobana/pyjobana.py
findjobana/shixiseng1.py
pyjobana/__init__.py
pyjobana/processor.py
pyjobana/pyjobana.py
pyjobana/spider.py
pyjobana-0.0.5.dist-info/METADATA
pyjobana-0.0.5.dist-info/RECORD
pyjobana-0.0.5.dist-info/WHEEL
pyjobana-0.0.5.dist-info/top_level.txt
