Metadata-Version: 2.1
Name: pyjobana
Version: 0.0.5
Summary: download and anaylis job
Home-page: https://github.com/prefect12/jobFinder
Author: Example Author
Author-email: jqmhpj@gmail.com
License: UNKNOWN
Platform: UNKNOWN
Classifier: Programming Language :: Python :: 3
Classifier: License :: OSI Approved :: MIT License
Classifier: Operating System :: OS Independent
Requires-Python: >=3.6
